mbedutils/__init__.py
mbedutils/rpc/__init__.py
mbedutils/rpc/client.py
mbedutils/rpc/messages.py
mbedutils/rpc/observers.py
mbedutils/rpc/parameters.py
mbedutils/rpc/pipe.py
mbedutils/rpc/socket.py
mbedutils/rpc/utility.py
mbedutils-0.1.0.dist-info/METADATA
mbedutils-0.1.0.dist-info/WHEEL
mbedutils-0.1.0.dist-info/RECORD
