Metadata-Version: 2.1
Name: mbedutils
Version: 0.1.0
Summary: Drivers and utilities to accompany my mbedutils C++ library
License: MIT
Author: Brandon Braun
Author-email: brandonbraun653@protonmail.com
Requires-Python: >=3.10,<4.0
Classifier: License :: OSI Approved :: MIT License
Classifier: Programming Language :: Python :: 3
Classifier: Programming Language :: Python :: 3.10
Classifier: Programming Language :: Python :: 3.11
Classifier: Programming Language :: Python :: 3.12
Requires-Dist: cobs
